[{"stockType":"Used","title":"2019 Lexus GX 460 Base","mileage":"15,019 mi.","primaryPrice":"$50,998","loanPrice":"","badges":["Good Deal","Home Delivery"]},{"stockType":"Kia Certified","title":"2019 Kia Forte LXS","mileage":"18,509 mi.","primaryPrice":"$23,126","loanPrice":"","badges":["Good Deal","CPO Warrantied","Home Delivery","Virtual Appointments"]},{"stockType":"Used","title":"2015 BMW 535 i","mileage":"62,500 mi.","primaryPrice":"$25,000","loanPrice":"","badges":["Fair Deal","Hot Car","Home Delivery","Virtual Appointments"]},{"stockType":"Mercedes-Benz Certified","title":"2019 Mercedes-Benz GLC 300 Base 4MATIC","mileage":"16,618 mi.","primaryPrice":"$41,070","loanPrice":"","badges":["Good Deal","CPO Warrantied","Home Delivery","Virtual Appointments"]},{"stockType":"Used","title":"2019 Chevrolet Trax LT","mileage":"24,911 mi.","primaryPrice":"$21,927","loanPrice":"","badges":["Good Deal","Home Delivery","Virtual Appointments"]},{"stockType":"Used","title":"2005 Ford Mustang GT Premium","mileage":"67,462 mi.","primaryPrice":"$20,900","loanPrice":"","badges":["Home Delivery","Virtual Appointments"]},{"stockType":"Used","title":"2020 Ford F-150 Lariat","mileage":"14,774 mi.","primaryPrice":"$52,995","loanPrice":"","badges":["Good Deal","Home Delivery","Virtual Appointments"]},{"stockType":"Used","title":"2019 BMW 540 i xDrive","mileage":"55,595 mi.","primaryPrice":"$42,500","loanPrice":"","badges":["Good Deal"]},{"stockType":"Used","title":"2019 Mercedes-Benz C-Class C 300","mileage":"34,034 mi.","primaryPrice":"$35,000","loanPrice":"","badges":["Good Deal"]},{"stockType":"Used","title":"2020 Lexus NX 300 F Sport","mileage":"33,062 mi.","primaryPrice":"$40,999","loanPrice":"","badges":["Good Deal","Home Delivery","Virtual Appointments"]},{"stockType":"Used","title":"2019 Lincoln Nautilus Select","mileage":"71,707 mi.","primaryPrice":"$33,790","loanPrice":"","badges":["Great Deal | $528 under","Home Delivery","Virtual Appointments"]},{"stockType":"Used","title":"2021 Subaru Outback Touring XT","mileage":"1,983 mi.","primaryPrice":"$38,155","loanPrice":"","badges":["Great Deal | $4,467 under","Home Delivery","Virtual Appointments"]},{"stockType":"Used","title":"2021 GMC Yukon SLT","mileage":"23,361 mi.","primaryPrice":"$74,880","loanPrice":"","badges":["Fair Deal"]},{"stockType":"Used","title":"2018 Ford F-150 Platinum","mileage":"42,500 mi.","primaryPrice":"$49,981","loanPrice":"","badges":["Great Deal","Home Delivery","Virtual Appointments"]},{"stockType":"Cadillac Certified","title":"2019 Cadillac XT4 Premium Luxury","mileage":"21,428 mi.","primaryPrice":"$35,933","loanPrice":"","badges":["Great Deal","CPO Warrantied","Home Delivery","Virtual Appointments"]},{"stockType":"Used","title":"2018 Mercedes-Benz GLE 350 Base 4MATIC","mileage":"55,330 mi.","primaryPrice":"$41,998","loanPrice":"","badges":["Fair Deal","Home Delivery"]},{"stockType":"Used","title":"2019 Hyundai Santa Fe Ultimate 2.4","mileage":"31,071 mi.","primaryPrice":"$32,997","loanPrice":"","badges":["Good Deal","Hot Car","Home Delivery","Virtual Appointments"]},{"stockType":"Toyota Certified","title":"2021 Toyota Highlander XLE","mileage":"11,599 mi.","primaryPrice":"$43,982","loanPrice":"","badges":["Good Deal","CPO Warrantied","Home Delivery","Virtual Appointments"]},{"stockType":"BMW Certified","title":"2019 BMW X3 sDrive30i","mileage":"30,395 mi.","primaryPrice":"$37,900","loanPrice":"","badges":["Good Deal","CPO Warrantied","Home Delivery","Virtual Appointments"]},{"stockType":"BMW Certified","title":"2021 BMW 330 i","mileage":"13,487 mi.","primaryPrice":"$44,988","loanPrice":"","badges":["Good Deal","CPO Warrantied","Home Delivery","Virtual Appointments"]},{"stockType":"Used","title":"2013 Volkswagen Tiguan SEL","mileage":"150,087 mi.","primaryPrice":"$7,499","loanPrice":"","badges":["Great Deal | $1,152 under","Virtual Appointments"]},{"stockType":"Used","title":"2018 Audi S5 Prestige","mileage":"28,917 mi.","primaryPrice":"$51,495","loanPrice":"","badges":["Good Deal","Home Delivery","Virtual Appointments"]},{"stockType":"Used","title":"2020 RAM 1500 Big Horn","mileage":"18,829 mi.","primaryPrice":"$45,998","loanPrice":"","badges":["Good Deal"]},{"stockType":"Used","title":"2020 Lexus LX 570 Three-Row","mileage":"10,816 mi.","primaryPrice":"$88,651","loanPrice":"","badges":["Good Deal","Home Delivery","Virtual Appointments"]},{"stockType":"Used","title":"2019 Lexus RX 350 350 PACKAGE!","mileage":"29,019 mi.","primaryPrice":"$45,620","loanPrice":"","badges":["Good Deal","Home Delivery","Virtual Appointments"]},{"stockType":"Used","title":"2019 Toyota Highlander XLE","mileage":"49,688 mi.","primaryPrice":"$36,999","loanPrice":"","badges":["Good Deal","Home Delivery","Virtual Appointments"]},{"stockType":"Used","title":"2019 Kia Sorento LX","mileage":"30,880 mi.","primaryPrice":"$28,577","loanPrice":"","badges":["Good Deal","Home Delivery","Virtual Appointments"]},{"stockType":"Used","title":"2015 INFINITI Q50 Premium","mileage":"109,142 mi.","primaryPrice":"$20,495","loanPrice":"","badges":["Fair Deal","Hot Car"]},{"stockType":"Used","title":"2017 Chevrolet Corvette Grand Sport","mileage":"16,110 mi.","primaryPrice":"$70,971","loanPrice":"","badges":["Good Deal","Home Delivery","Virtual Appointments"]},{"stockType":"Used","title":"2017 GMC Acadia Limited Limited","mileage":"60,866 mi.","primaryPrice":"$28,998","loanPrice":"","badges":["Good Deal","Home Delivery"]},{"stockType":"Used","title":"2019 INFINITI QX60 Luxe","mileage":"42,938 mi.","primaryPrice":"$36,998","loanPrice":"","badges":["Good Deal","Hot Car","Home Delivery"]},{"stockType":"Used","title":"2019 Mercedes-Benz CLA 250 Base","mileage":"54,984 mi.","primaryPrice":"$27,498","loanPrice":"","badges":["Good Deal","Home Delivery","Virtual Appointments"]},{"stockType":"Used","title":"2019 Nissan Rogue Sport S","mileage":"16,518 mi.","primaryPrice":"$23,789","loanPrice":"","badges":["Good Deal"]},{"stockType":"Used","title":"2013 Chevrolet Corvette Grand Sport","mileage":"39,765 mi.","primaryPrice":"$41,995","loanPrice":"","badges":["Good Deal","Home Delivery","Virtual Appointments"]},{"stockType":"Used","title":"2020 BMW X7 xDrive40i","mileage":"27,602 mi.","primaryPrice":"$69,489","loanPrice":"","badges":["Good Deal","Home Delivery","Virtual Appointments"]},{"stockType":"Mercedes-Benz Certified","title":"2019 Mercedes-Benz E-Class E 450","mileage":"14,425 mi.","primaryPrice":"$53,787","loanPrice":"","badges":["Good Deal","CPO Warrantied","Home Delivery","Virtual Appointments"]},{"stockType":"Used","title":"2019 BMW M5 EXECUTIVE","mileage":"15,823 mi.","primaryPrice":"$86,975","loanPrice":"","badges":["Good Deal"]},{"stockType":"Used","title":"2021 Mercedes-Benz GLA 250 Base","mileage":"13,049 mi.","primaryPrice":"$40,996","loanPrice":"","badges":["Good Deal","Home Delivery","Virtual Appointments"]},{"stockType":"Used","title":"2019 Audi Q5 2.0T Premium Plus","mileage":"21,767 mi.","primaryPrice":"$42,781","loanPrice":"","badges":["Good Deal","Home Delivery","Virtual Appointments"]},{"stockType":"Used","title":"2016 Chevrolet Silverado 1500 LT","mileage":"35,328 mi.","primaryPrice":"$35,805","loanPrice":"","badges":["Good Deal","Home Delivery","Virtual Appointments"]},{"stockType":"Used","title":"2019 Honda CR-V EX-L","mileage":"40,929 mi.","primaryPrice":"$30,998","loanPrice":"","badges":["Good Deal","Home Delivery","Virtual Appointments"]},{"stockType":"RAM Certified","title":"2021 RAM 1500 Limited","mileage":"42,145 mi.","primaryPrice":"$61,980","loanPrice":"","badges":["Good Deal","CPO Warrantied","Home Delivery","Virtual Appointments"]},{"stockType":"Used","title":"2016 Ford Focus SE","mileage":"109,891 mi.","primaryPrice":"$11,669","loanPrice":"","badges":["Fair Deal","Home Delivery","Virtual Appointments"]},{"stockType":"Used","title":"2019 GMC Acadia SLE-2","mileage":"49,044 mi.","primaryPrice":"$29,900","loanPrice":"","badges":["Good Deal","Home Delivery","Virtual Appointments"]},{"stockType":"Used","title":"2019 Volvo XC60 T5 Momentum","mileage":"19,580 mi.","primaryPrice":"$42,998","loanPrice":"","badges":["Good Deal"]},{"stockType":"Used","title":"2020 Nissan Rogue SV","mileage":"45,358 mi.","primaryPrice":"$23,999","loanPrice":"","badges":["Great Deal | $370 under"]},{"stockType":"Used","title":"2019 GMC Sierra 1500 Denali","mileage":"32,326 mi.","primaryPrice":"$56,990","loanPrice":"","badges":["Great Deal | $1,416 under"]},{"stockType":"Used","title":"2020 Mazda CX-5 Grand Touring","mileage":"62,434 mi.","primaryPrice":"$27,890","loanPrice":"","badges":["Good Deal","Virtual Appointments"]},{"stockType":"Used","title":"2019 GMC Sierra 1500 Denali","mileage":"24,426 mi.","primaryPrice":"$60,998","loanPrice":"","badges":["Great Deal | $685 under","Home Delivery","Virtual Appointments"]},{"stockType":"Porsche Certified","title":"2018 Porsche Panamera 4S","mileage":"20,182 mi.","primaryPrice":"$87,899","loanPrice":"","badges":["Good Deal","CPO Warrantied","Home Delivery","Virtual Appointments"]},{"stockType":"Used","title":"2021 Jeep Grand Cherokee L Limited","mileage":"17,617 mi.","primaryPrice":"$48,989","loanPrice":"","badges":["Great Deal","Home Delivery","Virtual Appointments"]},{"stockType":"Used","title":"2017 Toyota Prius Prime Advanced","mileage":"65,792 mi.","primaryPrice":"$31,500","loanPrice":"","badges":[]},{"stockType":"Used","title":"2013 Ford F-150 Lariat","mileage":"156,936 mi.","primaryPrice":"$18,966","loanPrice":"","badges":["Great Deal | $194 under","Home Delivery","Virtual Appointments"]},{"stockType":"Used","title":"2018 GMC Sierra 2500 Denali","mileage":"26,066 mi.","primaryPrice":"$67,222","loanPrice":"","badges":["Good Deal","Home Delivery","Virtual Appointments"]},{"stockType":"Used","title":"2021 Chevrolet Tahoe High Country","mileage":"8,157 mi.","primaryPrice":"$79,998","loanPrice":"","badges":["Good Deal","Hot Car","Home Delivery","Virtual Appointments"]},{"stockType":"Used","title":"2021 Volkswagen Atlas Cross Sport 3.6L V6 SEL","mileage":"23,177 mi.","primaryPrice":"$42,592","loanPrice":"","badges":["Great Deal | $586 under","Home Delivery","Virtual Appointments"]},{"stockType":"Used","title":"2019 Lexus RX 350 PUSH START NAV VA RERA PCS LKA BSM ECO PARK/STEER","mileage":"12,528 mi.","primaryPrice":"$45,496","loanPrice":"","badges":["Good Deal","Home Delivery","Virtual Appointments"]},{"stockType":"Used","title":"2021 Chrysler Pacifica Hybrid Limited","mileage":"11,977 mi.","primaryPrice":"$54,990","loanPrice":"","badges":["Good Deal","Hot Car","Home Delivery","Virtual Appointments"]},{"stockType":"Used","title":"2019 Audi Q8 3.0T Premium","mileage":"46,108 mi.","primaryPrice":"$64,900","loanPrice":"","badges":["Good Deal"]},{"stockType":"Used","title":"2021 Toyota Highlander Platinum","mileage":"1,930 mi.","primaryPrice":"$50,994","loanPrice":"","badges":["Great Deal","Home Delivery","Virtual Appointments"]},{"stockType":"Used","title":"2020 Ford Explorer ST","mileage":"51,639 mi.","primaryPrice":"$45,991","loanPrice":"","badges":["Good Deal","Home Delivery","Virtual Appointments"]},{"stockType":"Used","title":"2019 Jeep Grand Cherokee Altitude","mileage":"35,167 mi.","primaryPrice":"$37,936","loanPrice":"","badges":["Good Deal","Home Delivery","Virtual Appointments"]},{"stockType":"Used","title":"2017 Jeep Grand Cherokee Limited","mileage":"72,834 mi.","primaryPrice":"$28,551","loanPrice":"","badges":["Good Deal"]},{"stockType":"Used","title":"2020 Chevrolet Suburban LT","mileage":"50,530 mi.","primaryPrice":"$46,900","loanPrice":"","badges":["Great Deal | $2,754 under","Home Delivery","Virtual Appointments"]},{"stockType":"Nissan Certified","title":"2019 Nissan Rogue SL","mileage":"60,727 mi.","primaryPrice":"$26,765","loanPrice":"","badges":["Good Deal","CPO Warrantied","Home Delivery","Virtual Appointments"]},{"stockType":"Used","title":"2018 Mercedes-Benz GLE 350 Base 4MATIC","mileage":"45,230 mi.","primaryPrice":"$42,475","loanPrice":"","badges":["Good Deal","Home Delivery","Virtual Appointments"]},{"stockType":"Used","title":"2019 Kia Sorento LX V6","mileage":"48,542 mi.","primaryPrice":"$25,209","loanPrice":"","badges":["Great Deal | $855 under","Home Delivery","Virtual Appointments"]},{"stockType":"Used","title":"2020 Lexus NX 300 Base","mileage":"17,067 mi.","primaryPrice":"$39,604","loanPrice":"","badges":["Good Deal","Home Delivery","Virtual Appointments"]},{"stockType":"Used","title":"2015 Lincoln MKC Base","mileage":"96,120 mi.","primaryPrice":"$17,991","loanPrice":"","badges":["Good Deal","Virtual Appointments"]},{"stockType":"Used","title":"2019 Volvo S60 T6 Inscription","mileage":"27,991 mi.","primaryPrice":"$39,074","loanPrice":"","badges":["Good Deal","Home Delivery","Virtual Appointments"]},{"stockType":"Nissan Certified","title":"2019 Nissan Altima 2.5 SV","mileage":"10,142 mi.","primaryPrice":"$25,900","loanPrice":"","badges":["Great Deal | $935 under","CPO Warrantied","Home Delivery","Virtual Appointments"]},{"stockType":"Used","title":"2015 Honda Pilot Touring","mileage":"105,186 mi.","primaryPrice":"$24,989","loanPrice":"","badges":["Fair Deal"]},{"stockType":"Toyota Certified","title":"2020 Toyota Tundra SR5","mileage":"22,995 mi.","primaryPrice":"$47,973","loanPrice":"","badges":["Good Deal","CPO Warrantied","Virtual Appointments"]},{"stockType":"Used","title":"2022 Tesla Model Y Long Range","mileage":"1,111 mi.","primaryPrice":"$75,370","loanPrice":"","badges":["Good Deal","Home Delivery","Virtual Appointments"]},{"stockType":"Used","title":"2020 Jeep Grand Cherokee Limited","mileage":"42,696 mi.","primaryPrice":"$37,842","loanPrice":"","badges":["Great Deal | $675 under","Home Delivery","Virtual Appointments"]},{"stockType":"Used","title":"2020 Jeep Grand Cherokee Limited","mileage":"28,468 mi.","primaryPrice":"$39,989","loanPrice":"","badges":["Good Deal","Home Delivery","Virtual Appointments"]},{"stockType":"Used","title":"2019 Lexus GX 460 Base","mileage":"36,949 mi.","primaryPrice":"$44,971","loanPrice":"","badges":["Good Deal","Home Delivery","Virtual Appointments"]},{"stockType":"Used","title":"2020 Chevrolet Suburban LT","mileage":"69,893 mi.","primaryPrice":"$44,700","loanPrice":"","badges":["Great Deal | $3,162 under","Home Delivery","Virtual Appointments"]},{"stockType":"Used","title":"2015 Dodge Durango Limited","mileage":"73,038 mi.","primaryPrice":"$22,295","loanPrice":"","badges":["Good Deal"]},{"stockType":"Used","title":"2017 Dodge Journey Crossroad","mileage":"80,615 mi.","primaryPrice":"$17,893","loanPrice":"","badges":["Good Deal","Home Delivery","Virtual Appointments"]},{"stockType":"Used","title":"2020 Mercedes-Benz GLE 450 AWD 4MATIC","mileage":"23,130 mi.","primaryPrice":"$67,791","loanPrice":"","badges":["Great Deal","Home Delivery","Virtual Appointments"]},{"stockType":"Used","title":"2019 Jeep Cherokee Limited","mileage":"16,967 mi.","primaryPrice":"$31,879","loanPrice":"","badges":["Great Deal | $706 under","Hot Car"]},{"stockType":"Used","title":"2017 Ford Explorer sport","mileage":"61,691 mi.","primaryPrice":"$29,995","loanPrice":"","badges":["Good Deal","Home Delivery","Virtual Appointments"]},{"stockType":"Used","title":"2020 Mazda CX-5 Grand Touring","mileage":"63,567 mi.","primaryPrice":"$27,776","loanPrice":"","badges":["Good Deal","Virtual Appointments"]},{"stockType":"Used","title":"2017 Dodge Durango Citadel","mileage":"62,660 mi.","primaryPrice":"$32,997","loanPrice":"","badges":["Good Deal","Home Delivery","Virtual Appointments"]},{"stockType":"Cadillac Certified","title":"2019 Cadillac CT6 3.6L Premium Luxury","mileage":"38,885 mi.","primaryPrice":"$46,739","loanPrice":"","badges":["Great Deal | $1,679 under","CPO Warrantied","Home Delivery","Virtual Appointments"]},{"stockType":"Used","title":"2014 Mercedes-Benz E-Class E 350","mileage":"47,361 mi.","primaryPrice":"$34,917","loanPrice":"","badges":["Good Deal"]},{"stockType":"Used","title":"2019 Audi Q8 3.0T Premium","mileage":"69,154 mi.","primaryPrice":"$59,998","loanPrice":"","badges":["Good Deal","Home Delivery","Virtual Appointments"]},{"stockType":"Used","title":"2019 Chevrolet Silverado 1500 Custom Trail Boss","mileage":"21,700 mi.","primaryPrice":"$44,998","loanPrice":"","badges":["Fair Deal"]},{"stockType":"Mercedes-Benz Certified","title":"2018 Mercedes-Benz GLS 450 Base 4MATIC","mileage":"51,410 mi.","primaryPrice":"$44,879","loanPrice":"","badges":["Great Deal | $7,003 under","CPO Warrantied","Home Delivery","Virtual Appointments"]},{"stockType":"Jeep Certified","title":"2019 Jeep Cherokee Limited","mileage":"35,504 mi.","primaryPrice":"$29,999","loanPrice":"","badges":["Good Deal","CPO Warrantied","Home Delivery","Virtual Appointments"]},{"stockType":"Nissan Certified","title":"2019 Nissan Rogue SL","mileage":"32,163 mi.","primaryPrice":"$28,420","loanPrice":"","badges":["Good Deal","CPO Warrantied","Home Delivery","Virtual Appointments"]},{"stockType":"Used","title":"2020 Honda Civic Sport","mileage":"18,065 mi.","primaryPrice":"$27,573","loanPrice":"","badges":["Good Deal","Home Delivery"]},{"stockType":"Used","title":"2018 Jeep Wrangler Unlimited Sport","mileage":"21,333 mi.","primaryPrice":"$32,950","loanPrice":"","badges":["Great Deal | $5,481 under","Home Delivery","Virtual Appointments"]},{"stockType":"Used","title":"2018 Mercedes-Benz AMG C 43 Base 4MATIC","mileage":"32,200 mi.","primaryPrice":"$48,444","loanPrice":"","badges":["Fair Deal","Home Delivery","Virtual Appointments"]},{"stockType":"Used","title":"2016 Mercedes-Benz E-Class E 350 4MATIC","mileage":"55,124 mi.","primaryPrice":"$26,999","loanPrice":"","badges":["Good Deal","Home Delivery","Virtual Appointments"]},{"stockType":"Used","title":"2021 Toyota RAV4 LE","mileage":"45,543 mi.","primaryPrice":"$30,777","loanPrice":"","badges":["Good Deal","Home Delivery","Virtual Appointments"]},{"stockType":"Used","title":"2018 Lexus GX 460 Base","mileage":"44,322 mi.","primaryPrice":"$45,998","loanPrice":"","badges":["Good Deal"]},{"stockType":"Used","title":"2020 Ford Transit-250 Base","mileage":"38,766 mi.","primaryPrice":"$55,493","loanPrice":"","badges":["Good Deal","Home Delivery","Virtual Appointments"]}]